opendiloco/__init__.py
opendiloco/main.py
opendiloco-0.2.0.dist-info/LICENSE
opendiloco-0.2.0.dist-info/METADATA
opendiloco-0.2.0.dist-info/WHEEL
opendiloco-0.2.0.dist-info/top_level.txt
opendiloco-0.2.0.dist-info/RECORD
