Metadata-Version: 2.1
Name: opendiloco
Version: 0.2.0
Summary: opendiloco package
Home-page: https://github.com/PrimeIntellect-ai/opendiloco
Author: Jack Min Ong
Author-email: jackmin@primeintellect.ai
Classifier: Programming Language :: Python :: 3
Classifier: License :: OSI Approved :: MIT License
Classifier: Operating System :: OS Independent
Requires-Python: >=3.8
License-File: LICENSE
